Metadata-Version: 1.0
Name: etipsapi
Version: 1.0.1
Summary: e-tips API
Home-page: https://bitbucket.org/leopardsoftware/pypi
Author: Justin Taylor
Author-email: jtaylor@depoel.co.uk
License: UNKNOWN
Platform: UNKNOWN
